CHANGES.txt
LICENSE.txt
README.txt
bootstrap.py
buildout.cfg
setup.py
src/getpaid/__init__.py
src/getpaid.discount.egg-info/PKG-INFO
src/getpaid.discount.egg-info/SOURCES.txt
src/getpaid.discount.egg-info/dependency_links.txt
src/getpaid.discount.egg-info/namespace_packages.txt
src/getpaid.discount.egg-info/not-zip-safe
src/getpaid.discount.egg-info/requires.txt
src/getpaid.discount.egg-info/top_level.txt
src/getpaid/discount/README.txt
src/getpaid/discount/__init__.py
src/getpaid/discount/configure.zcml
src/getpaid/discount/interfaces.py
src/getpaid/discount/overrides.zcml
src/getpaid/discount/profiles.zcml
src/getpaid/discount/setuphandlers.py
src/getpaid/discount/subscribers.py
src/getpaid/discount/version.txt
src/getpaid/discount/browser/__init__.py
src/getpaid/discount/browser/configure.zcml
src/getpaid/discount/browser/contentcontrol.py
src/getpaid/discount/browser/discount.py
src/getpaid/discount/browser/interfaces.py
src/getpaid/discount/browser/portlets25.py
src/getpaid/discount/browser/portlets/__init__.py
src/getpaid/discount/browser/portlets/configure.zcml
src/getpaid/discount/browser/portlets/portlets30.py
src/getpaid/discount/browser/templates/portlet_content_buyxgetxfreeable.pt
src/getpaid/discount/browser/templates/portlet_content_discountable.pt
src/getpaid/discount/browser/viewlets/__init__.py
src/getpaid/discount/browser/viewlets/configure.zcml
src/getpaid/discount/browser/viewlets/discount_code.pt
src/getpaid/discount/browser/viewlets/discount_listing.pt
src/getpaid/discount/browser/viewlets/viewlets.py
src/getpaid/discount/locales/getpaid.discount.pot
src/getpaid/discount/locales/fr/LC_MESSAGES/getpaid.discount.mo
src/getpaid/discount/locales/fr/LC_MESSAGES/getpaid.discount.po
src/getpaid/discount/locales/zh/LC_MESSAGES/getpaid.discount.mo
src/getpaid/discount/locales/zh/LC_MESSAGES/getpaid.discount.po
src/getpaid/discount/profiles/default/actionicons.xml
src/getpaid/discount/profiles/default/actions.xml
src/getpaid/discount/profiles/default/browserlayer.xml
src/getpaid/discount/profiles/default/getpaid.discount-default.txt
src/getpaid/discount/profiles/default/import_steps.xml
src/getpaid/discount/profiles/default/metadata.xml
src/getpaid/discount/profiles/default/portlets.xml
src/getpaid/discount/profiles/default/viewlets.xml