Metadata-Version: 1.0
Name: getpaid.discount
Version: 0.10
Summary: package for plone getpaid handling discounts
Home-page: http://code.google.com/p/getpaid
Author: Six Feet Up, Inc.
Author-email: info@sixfeetup.com
License: ZPL2.1
Platform: UNKNOWN
Classifier: Framework :: Plone
Classifier: Programming Language :: Python
Classifier: Topic :: Software Development :: Libraries :: Python Modules
